allow_extra_kwargs/__init__.py
allow_extra_kwargs/mypy.py
allow_extra_kwargs/py.typed
allow_extra_kwargs-0.1.1.post1.dist-info/METADATA
allow_extra_kwargs-0.1.1.post1.dist-info/WHEEL
allow_extra_kwargs-0.1.1.post1.dist-info/RECORD
