Metadata-Version: 2.1
Name: allow-extra-kwargs
Version: 0.1.1.post1
Summary: A plugin for mypy that allows extra kwargs in function calls
Author: Alexey Sukhorosov
Requires-Python: >=3.10
Classifier: Programming Language :: Python :: 3
Classifier: Programming Language :: Python :: 3.10
Classifier: Programming Language :: Python :: 3.11
Classifier: Programming Language :: Python :: 3.12
